calculo_factorial_paralelo/__init__.py
calculo_factorial_paralelo/main.py
calcular_factorial_paralelo-0.0.2.dist-info/LICENSE
calcular_factorial_paralelo-0.0.2.dist-info/METADATA
calcular_factorial_paralelo-0.0.2.dist-info/WHEEL
calcular_factorial_paralelo-0.0.2.dist-info/top_level.txt
calcular_factorial_paralelo-0.0.2.dist-info/RECORD
